{
    "playlist": {
        "track": [
            {
                "info": "http://www.rdio.com/artist/Rick_Astley/album/The_Greatest_Hits/", 
                "album": "The Greatest Hits", 
                "meta": [
                    {
                        "http://rdio.gitjay.com/track/id/": "t2910908"
                    }
                ], 
                "location": [
                    "http://rd.io/e/QVGOBDdzOP0"
                ], 
                "title": "Never Gonna Give You Up", 
                "duration": 211, 
                "image": "http://cdn3.rd.io/album/8/b/7/000000000003a7b8/square-200.jpg", 
                "identifier": [
                    "http://www.rdio.com/artist/Rick_Astley/album/The_Greatest_Hits/track/Never_Gonna_Give_You_Up/"
                ], 
                "creator": "Rick Astley", 
                "trackNum": 1
            }, 
            {
                "info": "http://www.rdio.com/artist/Rick_Astley/album/The_Greatest_Hits/", 
                "album": "The Greatest Hits", 
                "meta": [
                    {
                        "http://rdio.gitjay.com/track/id/": "t2910908"
                    }
                ], 
                "location": [
                    "http://rd.io/e/QVGOBDdzOP0"
                ], 
                "title": "Never Gonna Give You Up", 
                "duration": 211, 
                "image": "http://cdn3.rd.io/album/8/b/7/000000000003a7b8/square-200.jpg", 
                "identifier": [
                    "http://www.rdio.com/artist/Rick_Astley/album/The_Greatest_Hits/track/Never_Gonna_Give_You_Up/"
                ], 
                "creator": "Rick Astley", 
                "trackNum": 1
            }, 
            {
                "info": "http://www.rdio.com/artist/Rick_Astley/album/The_Greatest_Hits/", 
                "album": "The Greatest Hits", 
                "meta": [
                    {
                        "http://rdio.gitjay.com/track/id/": "t2910908"
                    }
                ], 
                "location": [
                    "http://rd.io/e/QVGOBDdzOP0"
                ], 
                "title": "Never Gonna Give You Up", 
                "duration": 211, 
                "image": "http://cdn3.rd.io/album/8/b/7/000000000003a7b8/square-200.jpg", 
                "identifier": [
                    "http://www.rdio.com/artist/Rick_Astley/album/The_Greatest_Hits/track/Never_Gonna_Give_You_Up/"
                ], 
                "creator": "Rick Astley", 
                "trackNum": 1
            }, 
            {
                "info": "http://www.rdio.com/artist/Rick_Astley/album/The_Greatest_Hits/", 
                "album": "The Greatest Hits", 
                "meta": [
                    {
                        "http://rdio.gitjay.com/track/id/": "t2910908"
                    }
                ], 
                "location": [
                    "http://rd.io/e/QVGOBDdzOP0"
                ], 
                "title": "Never Gonna Give You Up", 
                "duration": 211, 
                "image": "http://cdn3.rd.io/album/8/b/7/000000000003a7b8/square-200.jpg", 
                "identifier": [
                    "http://www.rdio.com/artist/Rick_Astley/album/The_Greatest_Hits/track/Never_Gonna_Give_You_Up/"
                ], 
                "creator": "Rick Astley", 
                "trackNum": 1
            }
        ], 
        "identifier": "http://www.rdio.com/people/dgouldin/playlists/566436/Rickroll/", 
        "meta": [
            {
                "http://rdio.gitjay.com/playlist/id/": "p566436"
            }
        ], 
        "location": "http://rd.io/x/QVGOBDNX9uU", 
        "title": "Rickroll", 
        "date": "2012-02-12T11:57:28-00:00", 
        "image": "http://m.rdio.com/_is/?aid=239544&w=200&h=200", 
        "creator": "David Gouldin", 
        "annotation": "NEVER GONNA NEVER GONNA NEVER GONNA"
    }
}